{
  "project_info": {
    "project_number": "969784010619",
    "firebase_url": "https://advertop-5cbe4.firebaseio.com",
    "project_id": "advertop-5cbe4",
    "storage_bucket": "advertop-5cbe4.appspot.com"
  },
  "client": [
    {
      "client_info": {
        "mobilesdk_app_id": "1:969784010619:android:a1fb6b4eb345e5a0",
        "android_client_info": {
          "package_name": "com.mobile.earnings"
        }
      },
      "oauth_client": [
        {
          "client_id": "969784010619-5koeoi55dtg4mi4ctpqm6nk39jt814pg.apps.googleusercontent.com",
          "client_type": 3
        }
      ],
      "api_key": [
        {
          "current_key": "AIzaSyByqGp94qsc7RfMBcIpqv_6PE7YVJ9SXDA"
        }
      ],
      "services": {
        "analytics_service": {
          "status": 1
        },
        "appinvite_service": {
          "status": 1,
          "other_platform_oauth_client": []
        },
        "ads_service": {
          "status": 2
        }
      }
    }
  ],
  "configuration_version": "1"
}